active_vision/__init__.py
active_vision/core.py
active_vision/utils.py
active_vision-0.4.2.dist-info/METADATA
active_vision-0.4.2.dist-info/WHEEL
active_vision-0.4.2.dist-info/licenses/LICENSE
active_vision-0.4.2.dist-info/RECORD
