Metadata-Version: 2.4
Name: active-vision
Version: 0.4.2
Summary: Active learning for computer vision.
Project-URL: Homepage, https://github.com/dnth/active-vision
Project-URL: Bug Tracker, https://github.com/dnth/active-vision/issues
License-File: LICENSE
Requires-Python: >=3.10
Requires-Dist: accelerate>=1.2.1
Requires-Dist: datasets>=3.2.0
Requires-Dist: fastai>=2.7.18
Requires-Dist: gradio>=5.12.0
Requires-Dist: ipykernel>=6.29.5
Requires-Dist: ipywidgets>=8.1.5
Requires-Dist: itables>=2.2.4
Requires-Dist: loguru>=0.7.3
Requires-Dist: seaborn>=0.13.2
Requires-Dist: timm>=1.0.13
Requires-Dist: transformers>=4.48.0
Requires-Dist: xinfer>=0.3.2
Provides-Extra: dev
Requires-Dist: black>=22.0; extra == 'dev'
Requires-Dist: flake8>=4.0; extra == 'dev'
Requires-Dist: isort>=5.0; extra == 'dev'
Requires-Dist: pytest>=7.0; extra == 'dev'
Provides-Extra: docs
Requires-Dist: ansi2html; extra == 'docs'
Requires-Dist: ipykernel; extra == 'docs'
Requires-Dist: jupyter; extra == 'docs'
Requires-Dist: livereload; extra == 'docs'
Requires-Dist: mkdocs; extra == 'docs'
Requires-Dist: mkdocs-git-revision-date-localized-plugin; extra == 'docs'
Requires-Dist: mkdocs-git-revision-date-plugin; extra == 'docs'
Requires-Dist: mkdocs-jupyter>=0.24.0; extra == 'docs'
Requires-Dist: mkdocs-material>=9.1.3; extra == 'docs'
Requires-Dist: mkdocs-mermaid2-plugin; extra == 'docs'
Requires-Dist: mkdocs-pdf-export-plugin; extra == 'docs'
Requires-Dist: mkdocstrings; extra == 'docs'
Requires-Dist: mkdocstrings-crystal; extra == 'docs'
Requires-Dist: mkdocstrings-python-legacy; extra == 'docs'
Requires-Dist: nbconvert; extra == 'docs'
Requires-Dist: nbformat; extra == 'docs'
Requires-Dist: pygments; extra == 'docs'
Requires-Dist: pymdown-extensions; extra == 'docs'
Requires-Dist: sphinx; extra == 'docs'
Requires-Dist: watchdog; extra == 'docs'
